MANIFEST.in
README.txt
setup.cfg
setup.py
wwp/__init__.py
wwp.translate.egg-info/PKG-INFO
wwp.translate.egg-info/SOURCES.txt
wwp.translate.egg-info/dependency_links.txt
wwp.translate.egg-info/entry_points.txt
wwp.translate.egg-info/namespace_packages.txt
wwp.translate.egg-info/not-zip-safe
wwp.translate.egg-info/paster_plugins.txt
wwp.translate.egg-info/requires.txt
wwp.translate.egg-info/top_level.txt
wwp/translate/README.txt
wwp/translate/__init__.py
wwp/translate/config.py
wwp/translate/configure.zcml
wwp/translate/browser/__init__.py
wwp/translate/browser/configure.zcml
wwp/translate/browser/translatefolderview.pt
wwp/translate/browser/translatefolderview.py
wwp/translate/browser/wwp_translateview.pt
wwp/translate/browser/wwp_translateview.py
wwp/translate/content/__init__.py
wwp/translate/content/configure.zcml
wwp/translate/content/translatefolder.py
wwp/translate/content/wwp_translate.py
wwp/translate/interfaces/__init__.py
wwp/translate/interfaces/translatefolder.py
wwp/translate/interfaces/wwp_translate.py
wwp/translate/portlets/__init__.py
wwp/translate/portlets/configure.zcml
wwp/translate/profiles/default/factorytool.xml
wwp/translate/profiles/default/metadata.xml
wwp/translate/profiles/default/portlets.xml
wwp/translate/profiles/default/rolemap.xml
wwp/translate/profiles/default/types.xml
wwp/translate/profiles/default/types/translatefolder.xml
wwp/translate/profiles/default/types/wwp_translate.xml
wwp/translate/tests/__init__.py
wwp/translate/tests/base.py
wwp/translate/tests/test_doctest.py