Metadata-Version: 1.0
Name: wwp.translate
Version: 0.1dev
Summary: Translate text using google translate api
Home-page: http://svn.plone.org/svn/plone/plone.example
Author: Peter Dyson
Author-email: pjdyson@gmail.com
License: GPL
Keywords: wwp plone translate language languages api international google
Platform: UNKNOWN
Classifier: Framework :: Plone
Classifier: Intended Audience :: Developers
Classifier: Topic :: Software Development :: Libraries :: Python Modules
Classifier: License :: OSI Approved :: GNU General Public License (GPL)
